odoo/addons/analytic_partner_hr_timesheet/README.rst
odoo/addons/analytic_partner_hr_timesheet/__init__.py
odoo/addons/analytic_partner_hr_timesheet/__manifest__.py
odoo/addons/analytic_partner_hr_timesheet/i18n/am.po
odoo/addons/analytic_partner_hr_timesheet/i18n/analytic_partner_hr_timesheet.pot
odoo/addons/analytic_partner_hr_timesheet/i18n/ar.po
odoo/addons/analytic_partner_hr_timesheet/i18n/bg.po
odoo/addons/analytic_partner_hr_timesheet/i18n/bs.po
odoo/addons/analytic_partner_hr_timesheet/i18n/ca.po
odoo/addons/analytic_partner_hr_timesheet/i18n/cs.po
odoo/addons/analytic_partner_hr_timesheet/i18n/cs_CZ.po
odoo/addons/analytic_partner_hr_timesheet/i18n/da.po
odoo/addons/analytic_partner_hr_timesheet/i18n/de.po
odoo/addons/analytic_partner_hr_timesheet/i18n/el_GR.po
odoo/addons/analytic_partner_hr_timesheet/i18n/en_GB.po
odoo/addons/analytic_partner_hr_timesheet/i18n/es.po
odoo/addons/analytic_partner_hr_timesheet/i18n/es_CR.po
odoo/addons/analytic_partner_hr_timesheet/i18n/es_EC.po
odoo/addons/analytic_partner_hr_timesheet/i18n/es_MX.po
odoo/addons/analytic_partner_hr_timesheet/i18n/es_VE.po
odoo/addons/analytic_partner_hr_timesheet/i18n/et.po
odoo/addons/analytic_partner_hr_timesheet/i18n/eu.po
odoo/addons/analytic_partner_hr_timesheet/i18n/fi.po
odoo/addons/analytic_partner_hr_timesheet/i18n/fr.po
odoo/addons/analytic_partner_hr_timesheet/i18n/fr_CA.po
odoo/addons/analytic_partner_hr_timesheet/i18n/fr_CH.po
odoo/addons/analytic_partner_hr_timesheet/i18n/gl.po
odoo/addons/analytic_partner_hr_timesheet/i18n/hr.po
odoo/addons/analytic_partner_hr_timesheet/i18n/hr_HR.po
odoo/addons/analytic_partner_hr_timesheet/i18n/hu.po
odoo/addons/analytic_partner_hr_timesheet/i18n/it.po
odoo/addons/analytic_partner_hr_timesheet/i18n/ja.po
odoo/addons/analytic_partner_hr_timesheet/i18n/lt.po
odoo/addons/analytic_partner_hr_timesheet/i18n/lv.po
odoo/addons/analytic_partner_hr_timesheet/i18n/mk.po
odoo/addons/analytic_partner_hr_timesheet/i18n/mn.po
odoo12_addon_analytic_partner_hr_timesheet-12.0.1.1.0.dist-info/METADATA
odoo12_addon_analytic_partner_hr_timesheet-12.0.1.1.0.dist-info/WHEEL
odoo12_addon_analytic_partner_hr_timesheet-12.0.1.1.0.dist-info/top_level.txt
odoo12_addon_analytic_partner_hr_timesheet-12.0.1.1.0.dist-info/RECORD
